pyomocontrib_simplemodel/__init__.py
pyomocontrib_simplemodel/core.py
pyomocontrib_simplemodel/tests/__init__.py
pyomocontrib_simplemodel/tests/test_examples.py
pyomocontrib_simplemodel-1.0.2.dist-info/LICENSE.txt
pyomocontrib_simplemodel-1.0.2.dist-info/METADATA
pyomocontrib_simplemodel-1.0.2.dist-info/WHEEL
pyomocontrib_simplemodel-1.0.2.dist-info/top_level.txt
pyomocontrib_simplemodel-1.0.2.dist-info/RECORD
