Metadata-Version: 2.1
Name: pyomocontrib-simplemodel
Version: 1.0.2
Summary: An optimization modeling tool for LP and NLP
Home-page: http://pyomo.org
Maintainer: William E. Hart
Maintainer-email: wehart@sandia.gov
License: BSD
Keywords: optimization
Platform: any
Classifier: Development Status :: 4 - Beta
Classifier: Intended Audience :: End Users/Desktop
Classifier: Intended Audience :: Science/Research
Classifier: License :: OSI Approved :: BSD License
Classifier: Natural Language :: English
Classifier: Operating System :: Microsoft :: Windows
Classifier: Operating System :: Unix
Classifier: Programming Language :: Python
Classifier: Programming Language :: Unix Shell
Classifier: Topic :: Scientific/Engineering :: Mathematics
Classifier: Topic :: Software Development :: Libraries :: Python Modules
Requires-Dist: Pyomo (>=5.6)
